setup.py
src/plone/__init__.py
src/plone.recipe.plone21install.egg-info/PKG-INFO
src/plone.recipe.plone21install.egg-info/SOURCES.txt
src/plone.recipe.plone21install.egg-info/dependency_links.txt
src/plone.recipe.plone21install.egg-info/entry_points.txt
src/plone.recipe.plone21install.egg-info/namespace_packages.txt
src/plone.recipe.plone21install.egg-info/requires.txt
src/plone.recipe.plone21install.egg-info/top_level.txt
src/plone/recipe/__init__.py
src/plone/recipe/plone21install/__init__.py
