Metadata-Version: 1.0
Name: plone.recipe.plone21install
Version: 1.0
Summary: ZC Buildout recipe for installing Plone 2.1.
Home-page: http://svn.plone.org/svn/collective/buildout/plone.recipe.plone21install/trunk
Author: Sidnei da Silva
Author-email: sidnei@enfoldsystems.com
License: ZPL 2.1
Keywords: zope2 buildout
Platform: UNKNOWN
Classifier: License :: OSI Approved :: Zope Public License
Classifier: Framework :: Zope2
Classifier: Framework :: Buildout
Classifier: Programming Language :: Python
